renogymodbus/__init__.py
renogymodbus/command_line.py
renogymodbus/driver.py
renogymodbus/extract_bits.py
renogymodbus-0.0.15.dist-info/LICENSE
renogymodbus-0.0.15.dist-info/METADATA
renogymodbus-0.0.15.dist-info/WHEEL
renogymodbus-0.0.15.dist-info/entry_points.txt
renogymodbus-0.0.15.dist-info/top_level.txt
renogymodbus-0.0.15.dist-info/RECORD
